pyimp/__init__.py
pyimp/utils.py
pyimpcheck-0.2.0.dist-info/METADATA
pyimpcheck-0.2.0.dist-info/WHEEL
pyimpcheck-0.2.0.dist-info/top_level.txt
pyimpcheck-0.2.0.dist-info/RECORD
