Metadata-Version: 2.4
Name: pyimpcheck
Version: 0.2.0
Summary: Thonny python module that checks if the library is installed or not, if not, then it will install and import it automatically
Home-page: https://github.com/hibro114/pyimp
Author: Cheng
Author-email: xcxhxxg08@gmail.com
Classifier: Programming Language :: Python :: 3
Classifier: License :: OSI Approved :: MIT License
Classifier: Operating System :: OS Independent
Requires-Python: >=3.6
Dynamic: author
Dynamic: author-email
Dynamic: classifier
Dynamic: description
Dynamic: description-content-type
Dynamic: home-page
Dynamic: requires-python
Dynamic: summary
